collectd_eos/__init__.py
collectd_eos/gentypes.py
collectd_eos-0.2.1.dist-info/LICENSE
collectd_eos-0.2.1.dist-info/METADATA
collectd_eos-0.2.1.dist-info/WHEEL
collectd_eos-0.2.1.dist-info/top_level.txt
collectd_eos-0.2.1.dist-info/zip-safe
collectd_eos-0.2.1.dist-info/RECORD
