Metadata-Version: 2.1
Name: collectd-eos
Version: 0.2.1
Summary: Collectd plugin to monitor EOS MGM metrics.
Home-page: https://gitlab.cern.ch/ikadochn/collectd-eos
Author: Ivan Kadochnikov
Author-email: ivan.kadochikov@cern.ch
License: UNKNOWN
Keywords: collectd eos storage monitoring
Platform: UNKNOWN
Classifier: Development Status :: 2 - Pre-Alpha
Classifier: License :: OSI Approved :: Apache Software License
Classifier: Intended Audience :: System Administrators
Classifier: Operating System :: POSIX :: Linux
Classifier: Programming Language :: Python
Classifier: Programming Language :: Python :: 2
Classifier: Programming Language :: Python :: 2.7
Classifier: Programming Language :: Python :: 3
Classifier: Programming Language :: Python :: 3.5
Classifier: Programming Language :: Python :: 3.6
Classifier: Programming Language :: Python :: 3.7
Classifier: Topic :: System :: Monitoring
